calsched/__init__.py
calsched/core.py
calsched/py.typed
calsched-1.1.1.dist-info/METADATA
calsched-1.1.1.dist-info/WHEEL
calsched-1.1.1.dist-info/licenses/LICENSE
calsched-1.1.1.dist-info/RECORD
