Metadata-Version: 2.4
Name: calsched
Version: 1.1.1
Summary: Calendar scheduler
Project-URL: Repository, https://github.com/bravikov/calsched
Project-URL: Issues, https://github.com/bravikov/calsched/issues
Author-email: Dmitry Bravikov <dmitry@bravikov.ru>
License-Expression: MIT
License-File: LICENSE
Classifier: Operating System :: OS Independent
Classifier: Programming Language :: Python :: 3
Requires-Python: >=3.8
